[{"date":"Tue, 05 Jan 2016 11:56:47 GMT","sloc":12,"lloc":8,"functions":1,"deliveredBugs":0.04245906842019469,"maintainability":73.74094038130144,"lintErrors":[],"difficulty":4.25},{"date":"Tue, 05 Jan 2016 12:07:22 GMT","sloc":12,"lloc":8,"functions":1,"deliveredBugs":0.04245906842019469,"maintainability":73.74094038130144,"lintErrors":[],"difficulty":4.25},{"date":"Tue, 05 Jan 2016 12:11:57 GMT","sloc":12,"lloc":8,"functions":1,"deliveredBugs":0.04245906842019469,"maintainability":73.74094038130144,"lintErrors":[],"difficulty":4.25},{"date":"Tue, 05 Jan 2016 12:18:11 GMT","sloc":12,"lloc":8,"functions":1,"deliveredBugs":0.04245906842019469,"maintainability":73.74094038130144,"lintErrors":[],"difficulty":4.25}]